Workbook

Sheet Income Statement
B1: RETAIL SME - INCOME STATEMENT (Monthly, Jan 2023 - Dec 2025, USD)
B3: Line Item | C3: Jan-23 | D3: Feb-23 | E3: Mar-23 | F3: Apr-23 | G3: May-23 | H3: Jun-23 | I3: Jul-23 | J3: Aug-23 | K3: Sep-23 | L3: Oct-23 | M3: Nov-23 | N3: Dec-23 | O3: Jan-24 | P3: Feb-24 | Q3: Mar-24 | R3: Apr-24 | S3: May-24 | T3: Jun-24 | U3: Jul-24 | V3: Aug-24 | W3: Sep-24 | X3: Oct-24 | Y3: Nov-24 | Z3: Dec-24 | AA3: Jan-25 | AB3: Feb-25 | AC3: Mar-25 | AD3: Apr-25 | AE3: May-25 | AF3: Jun-25 | AG3: Jul-25 | AH3: Aug-25 | AI3: Sep-25 | AJ3: Oct-25 | AK3: Nov-25 | AL3: Dec-25
B4: Revenue - Product Sales | C4: 22956 | D4: 23919 | E4: 23684 | F4: 30399 | G4: 28486 | H4: 27823 | I4: 27366 | J4: 29238 | K4: 29761 | L4: 35339 | M4: 39395 | N4: 52841 | O4: 25966 | P4: 25030 | Q4: 33591 | R4: 33780 | S4: 34252 | T4: 29286 | U4: 30338 | V4: 31632 | W4: 38577 | X4: 41296 | Y4: 44180 | Z4: 60833 | AA4: 30162 | AB4: 33428 | AC4: 37042 | AD4: 40457 | AE4: 37009 | AF4: 38501 | AG4: 36428 | AH4: 34963 | AI4: 41639 | AJ4: 46244 | AK4: 45898 | AL4: 67065
B5: Revenue - Other | C5: 963 | D5: 986 | E5: 681 | F5: 790 | G5: 1154 | H5: 817 | I5: 1304 | J5: 898 | K5: 600 | L5: 830 | M5: 1836 | N5: 1840 | O5: 1226 | P5: 1199 | Q5: 1575 | R5: 683 | S5: 1407 | T5: 836 | U5: 1052 | V5: 982 | W5: 791 | X5: 1986 | Y5: 1586 | Z5: 1854 | AA5: 612 | AB5: 1322 | AC5: 1372 | AD5: 1892 | AE5: 1784 | AF5: 1887 | AG5: 1752 | AH5: 1620 | AI5: 1974 | AJ5: 2160 | AK5: 1732 | AL5: 2890
B6: Total Revenue | C6: =C4+C5 -> 23919 | D6: =D4+D5 -> 24905 | E6: =E4+E5 -> 24365 | F6: =F4+F5 -> 31189 | G6: =G4+G5 -> 29640 | H6: =H4+H5 -> 28640 | I6: =I4+I5 -> 28670 | J6: =J4+J5 -> 30136 | ... AL6: =AL4+AL5 -> 69955
B7: COGS | C7: 14732 | D7: 14476 | E7: 15026 | F7: 19052 | G7: 17974 | H7: 17505 | I7: 16781 | J7: 17987 | K7: 19095 | L7: 22851 | M7: 25082 | N7: 33430 | O7: 16178 | P7: 16485 | Q7: 21067 | R7: 21045 | S7: 21460 | T7: 17537 | U7: 20063 | V7: 20153 | W7: 24043 | X7: 25461 | Y7: 27208 | Z7: 39089 | AA7: 18036 | AB7: 20623 | AC7: 22496 | AD7: 26166 | AE7: 24720 | AF7: 25760 | AG7: 23739 | AH7: 22844 | AI7: 26634 | AJ7: 29056 | AK7: 27713 | AL7: 41480
B8: Gross Profit | C8: =C6-C7 -> 9187 | D8: =D6-D7 -> 10429 | E8: =E6-E7 -> 9339 | F8: =F6-F7 -> 12137 | G8: =G6-G7 -> 11666 | H8: =H6-H7 -> 11135 | I8: =I6-I7 -> 11889 | J8: =J6-J7 -> 12149 | ... AL8: =AL6-AL7 -> 28475
B9: Gross Margin % | C9: =IFERROR(C8/C6,0) -> 0.38408796 | D9: =IFERROR(D8/D6,0) -> 0.41875125 | E9: =IFERROR(E8/E6,0) -> 0.38329571 | F9: =IFERROR(F8/F6,0) -> 0.38914361 | G9: =IFERROR(G8/G6,0) -> 0.39358974 | H9: =IFERROR(H8/H6,0) -> 0.3887919 | I9: =IFERROR(I8/I6,0) -> 0.41468434 | J9: =IFERROR(J8/J6,0) -> 0.4031391 | ... AL9: =IFERROR(AL8/AL6,0) -> 0.40704739
B10: Rent | C10: 1200 | D10: 1200 | E10: 1200 | F10: 1200 | G10: 1200 | H10: 1200 | I10: 1200 | J10: 1200 | K10: 1200 | L10: 1200 | M10: 1200 | N10: 1200 | O10: 1200 | P10: 1200 | Q10: 1200 | R10: 1200 | S10: 1200 | T10: 1200 | U10: 1200 | V10: 1200 | W10: 1200 | X10: 1200 | Y10: 1200 | Z10: 1200 | AA10: 1200 | AB10: 1200 | AC10: 1200 | AD10: 1200 | AE10: 1200 | AF10: 1200 | AG10: 1200 | AH10: 1200 | AI10: 1200 | AJ10: 1200 | AK10: 1200 | AL10: 1200
B11: Salaries & Wages | C11: 6500 | D11: 6532 | E11: 6565 | F11: 6598 | G11: 6631 | H11: 6664 | I11: 6697 | J11: 6731 | K11: 6765 | L11: 6798 | M11: 6832 | N11: 6867 | O11: 6901 | P11: 6935 | Q11: 6970 | R11: 7005 | S11: 7040 | T11: 7075 | U11: 7111 | V11: 7146 | W11: 7182 | X11: 7218 | Y11: 7254 | Z11: 7290 | AA11: 7327 | AB11: 7363 | AC11: 7400 | AD11: 7437 | AE11: 7474 | AF11: 7512 | AG11: 7549 | AH11: 7587 | AI11: 7625 | AJ11: 7663 | AK11: 7701 | AL11: 7740
B12: Utilities | C12: 434 | D12: 613 | E12: 431 | F12: 530 | G12: 427 | H12: 520 | I12: 443 | J12: 519 | K12: 556 | L12: 537 | M12: 426 | N12: 494 | O12: 490 | P12: 539 | Q12: 424 | R12: 492 | S12: 614 | T12: 534 | U12: 453 | V12: 539 | W12: 450 | X12: 475 | Y12: 420 | Z12: 597 | AA12: 546 | AB12: 557 | AC12: 481 | AD12: 575 | AE12: 601 | AF12: 588 | AG12: 525 | AH12: 553 | AI12: 510 | AJ12: 483 | AK12: 408 | AL12: 537
B13: Marketing | C13: 415 | D13: 685 | E13: 472 | F13: 490 | G13: 665 | H13: 509 | I13: 449 | J13: 516 | K13: 787 | L13: 722 | M13: 1060 | N13: 841 | O13: 716 | P13: 736 | Q13: 648 | R13: 632 | S13: 1050 | T13: 679 | U13: 787 | V13: 751 | W13: 972 | X13: 723 | Y13: 1302 | Z13: 1774 | AA13: 464 | AB13: 645 | AC13: 729 | AD13: 955 | AE13: 797 | AF13: 784 | AG13: 628 | AH13: 934 | AI13: 1176 | AJ13: 794 | AK13: 1302 | AL13: 1139
B14: Transport & Logistics | C14: 499 | D14: 577 | E14: 621 | F14: 908 | G14: 608 | H14: 989 | I14: 713 | J14: 965 | K14: 958 | L14: 758 | M14: 1295 | N14: 1182 | O14: 637 | P14: 841 | Q14: 929 | R14: 751 | S14: 848 | T14: 626 | U14: 986 | V14: 696 | W14: 890 | X14: 1466 | Y14: 1533 | Z14: 1987 | AA14: 690 | AB14: 865 | AC14: 909 | AD14: 1213 | AE14: 785 | AF14: 1041 | AG14: 1116 | AH14: 929 | AI14: 1297 | AJ14: 1388 | AK14: 1210 | AL14: 1453
B15: Other Admin Expenses | C15: 696 | D15: 423 | E15: 532 | F15: 418 | G15: 714 | H15: 660 | I15: 505 | J15: 380 | K15: 380 | L15: 474 | M15: 575 | N15: 363 | O15: 381 | P15: 425 | Q15: 677 | R15: 485 | S15: 549 | T15: 461 | U15: 445 | V15: 684 | W15: 626 | X15: 701 | Y15: 603 | Z15: 607 | AA15: 569 | AB15: 649 | AC15: 739 | AD15: 547 | AE15: 721 | AF15: 690 | AG15: 746 | AH15: 467 | AI15: 631 | AJ15: 364 | AK15: 401 | AL15: 563
B16: Total Operating Expenses | C16: =C10+C11+C12+C13+C14+C15 -> 9744 | D16: =D10+D11+D12+D13+D14+D15 -> 10030 | E16: =E10+E11+E12+E13+E14+E15 -> 9821 | F16: =F10+F11+F12+F13+F14+F15 -> 10144 | G16: =G10+G11+G12+G13+G14+G15 -> 10245 | H16: =H10+H11+H12+H13+H14+H15 -> 10542 | I16: =I10+I11+I12+I13+I14+I15 -> 10007 | J16: =J10+J11+J12+J13+J14+J15 -> 10311 | ... AL16: =AL10+AL11+AL12+AL13+AL14+AL15 -> 12632
B17: Operating Profit (EBIT) | C17: =C8-C16 -> -557 | D17: =D8-D16 -> 399 | E17: =E8-E16 -> -482 | F17: =F8-F16 -> 1993 | G17: =G8-G16 -> 1421 | H17: =H8-H16 -> 593 | I17: =I8-I16 -> 1882 | J17: =J8-J16 -> 1838 | ... AL17: =AL8-AL16 -> 15843
B18: Other Income | C18: 0 | D18: 76 | E18: 0 | F18: 237 | G18: 166 | H18: 0 | I18: 207 | J18: 0 | K18: 0 | L18: 0 | M18: 0 | N18: 0 | O18: 40 | P18: 0 | Q18: 0 | R18: 0 | S18: 0 | T18: 0 | U18: 0 | V18: 0 | W18: 0 | X18: 165 | Y18: 0 | Z18: 40 | AA18: 0 | AB18: 0 | AC18: 0 | AD18: 181 | AE18: 0 | AF18: 0 | AG18: 130 | AH18: 0 | AI18: 0 | AJ18: 0 | AK18: 0 | AL18: 0
B19: Interest Expense | C19: 0 | D19: 0 | E19: 0 | F19: 0 | G19: 0 | H19: 0 | I19: 220 | J19: 220 | K19: 220 | L19: 220 | M19: 220 | N19: 220 | O19: 220 | P19: 220 | Q19: 220 | R19: 220 | S19: 220 | T19: 220 | U19: 220 | V19: 220 | W19: 220 | X19: 220 | Y19: 220 | Z19: 220 | AA19: 220 | AB19: 220 | AC19: 220 | AD19: 220 | AE19: 220 | AF19: 220 | AG19: 220 | AH19: 220 | AI19: 220 | AJ19: 220 | AK19: 220 | AL19: 220
B20: Profit Before Tax | C20: =C17+C18-C19 -> -557 | D20: =D17+D18-D19 -> 475 | E20: =E17+E18-E19 -> -482 | F20: =F17+F18-F19 -> 2230 | G20: =G17+G18-G19 -> 1587 | H20: =H17+H18-H19 -> 593 | I20: =I17+I18-I19 -> 1869 | J20: =J17+J18-J19 -> 1618 | ... AL20: =AL17+AL18-AL19 -> 15623
B21: Corporate Income Tax (21%) | C21: =MAX(C20*0.21,0) -> 0 | D21: =MAX(D20*0.21,0) -> 99.75 | E21: =MAX(E20*0.21,0) -> 0 | F21: =MAX(F20*0.21,0) -> 468.3 | G21: =MAX(G20*0.21,0) -> 333.27 | H21: =MAX(H20*0.21,0) -> 124.53 | I21: =MAX(I20*0.21,0) -> 392.49 | J21: =MAX(J20*0.21,0) -> 339.78 | ... AL21: =MAX(AL20*0.21,0) -> 3280.83
B22: Net Profit | C22: =C20-C21 -> -557 | D22: =D20-D21 -> 375.25 | E22: =E20-E21 -> -482 | F22: =F20-F21 -> 1761.7 | G22: =G20-G21 -> 1253.73 | H22: =H20-H21 -> 468.47 | I22: =I20-I21 -> 1476.51 | J22: =J20-J21 -> 1278.22 | ... AL22: =AL20-AL21 -> 12342.17
B23: Net Margin % | C23: =IFERROR(C22/C6,0) -> -0.023286927 | D23: =IFERROR(D22/D6,0) -> 0.015067256 | E23: =IFERROR(E22/E6,0) -> -0.019782475 | F23: =IFERROR(F22/F6,0) -> 0.056484658 | G23: =IFERROR(G22/G6,0) -> 0.042298583 | H23: =IFERROR(H22/H6,0) -> 0.016357193 | I23: =IFERROR(I22/I6,0) -> 0.051500174 | J23: =IFERROR(J22/J6,0) -> 0.042415052 | ... AL23: =IFERROR(AL22/AL6,0) -> 0.17643013
B26: Assumptions:
B27: - Blue cells = source data (editable inputs). Black/bold shaded cells = formulas, do not overwrite.
B28: - Corporate Income Tax modeled at a flat 21% for simplicity - adjust per actual jurisdiction/tax position.
B29: - Interest Expense begins Jul-2023, reflecting an assumed working-capital loan drawn mid-year.
B30: - Dataset is synthetic, generated to model a small retail/trading SME (USD) for internship dashboard purposes.

Sheet Balance Sheet
B1: RETAIL SME - BALANCE SHEET (Monthly, Jan 2023 - Dec 2025, USD)
B3: Line Item | C3: Jan-23 | D3: Feb-23 | E3: Mar-23 | F3: Apr-23 | G3: May-23 | H3: Jun-23 | I3: Jul-23 | J3: Aug-23 | K3: Sep-23 | L3: Oct-23 | M3: Nov-23 | N3: Dec-23 | O3: Jan-24 | P3: Feb-24 | Q3: Mar-24 | R3: Apr-24 | S3: May-24 | T3: Jun-24 | U3: Jul-24 | V3: Aug-24 | W3: Sep-24 | X3: Oct-24 | Y3: Nov-24 | Z3: Dec-24 | AA3: Jan-25 | AB3: Feb-25 | AC3: Mar-25 | AD3: Apr-25 | AE3: May-25 | AF3: Jun-25 | AG3: Jul-25 | AH3: Aug-25 | AI3: Sep-25 | AJ3: Oct-25 | AK3: Nov-25 | AL3: Dec-25
B4: Cash and Bank | C4: 14418 | D4: 12896.25 | E4: 13657.25 | F4: 8127.95 | G4: 11486.68 | H4: 7194.15 | I4: 21195.66 | J4: 18893.88 | K4: 17095.88 | L4: 10968.99 | M4: 11605.38 | N4: 9179.74 | O4: 28180.85 | P4: 25256.85 | Q4: 20296.34 | R4: 21449.41 | S4: 20143.03 | T4: 25182.13 | U4: 23007.88 | V4: 14587.63 | W4: 8931.78 | X4: 11888.35 | Y4: 11046.89 | Z4: 2017.66 | AA4: 32011.04 | AB4: 30022.16 | AC4: 28788.76 | AD4: 26646.19 | AE4: 27369.44 | AF4: 25132.91 | AG4: 26823.64 | AH4: 32138.35 | AI4: 26900.15 | AJ4: 32671.59 | AK4: 37081.84 | AL4: 28708.01
B5: Accounts Receivable | C5: 3422 | D5: 4207 | E5: 3899 | F5: 4990 | G5: 4601 | H5: 5052 | I5: 5082 | J5: 5364 | K5: 5355 | L5: 6149 | M5: 6110 | N5: 8700 | O5: 4643 | P5: 3962 | Q5: 5848 | R5: 5816 | S5: 5250 | T5: 4731 | U5: 4916 | V5: 5491 | W5: 7016 | X5: 6594 | Y5: 8174 | Z5: 9961 | AA5: 4688 | AB5: 5540 | AC5: 5876 | AD5: 6632 | AE5: 6667 | AF5: 6912 | AG5: 6568 | AH5: 6403 | AI5: 7496 | AJ5: 8052 | AK5: 8217 | AL5: 11831
B6: Inventory | C6: 18503 | D6: 18755 | E6: 16745 | F6: 23545 | G6: 20008 | H6: 20003 | I6: 18543 | J6: 20614 | K6: 21513 | L6: 28194 | M6: 30052 | N6: 39219 | O6: 18812 | P6: 19627 | Q6: 24734 | R6: 24888 | S6: 26787 | T6: 21516 | U6: 22075 | V6: 24282 | W6: 29731 | X6: 31025 | Y6: 35071 | Z6: 49576 | AA6: 21510 | AB6: 23250 | AC6: 26097 | AD6: 31128 | AE6: 29775 | AF6: 32907 | AG6: 30572 | AH6: 26392 | AI6: 33118 | AJ6: 32364 | AK6: 32855 | AL6: 52441
B7: Total Current Assets | C7: =C4+C5+C6 -> 36343 | D7: =D4+D5+D6 -> 35858.25 | E7: =E4+E5+E6 -> 34301.25 | F7: =F4+F5+F6 -> 36662.95 | G7: =G4+G5+G6 -> 36095.68 | H7: =H4+H5+H6 -> 32249.15 | I7: =I4+I5+I6 -> 44820.66 | J7: =J4+J5+J6 -> 44871.88 | ... AL7: =AL4+AL5+AL6 -> 92980.01
B8: Fixed Assets (Net) | C8: 20000 | D8: 20000 | E8: 20000 | F8: 20000 | G8: 20000 | H8: 23500 | I8: 23500 | J8: 23500 | K8: 23500 | L8: 23500 | M8: 23500 | N8: 23500 | O8: 23500 | P8: 23500 | Q8: 23500 | R8: 23500 | S8: 23500 | T8: 23500 | U8: 23500 | V8: 29500 | W8: 29500 | X8: 29500 | Y8: 29500 | Z8: 29500 | AA8: 29500 | AB8: 29500 | AC8: 29500 | AD8: 29500 | AE8: 29500 | AF8: 29500 | AG8: 29500 | AH8: 29500 | AI8: 29500 | AJ8: 29500 | AK8: 29500 | AL8: 29500
B9: Total Assets | C9: =C7+C8 -> 56343 | D9: =D7+D8 -> 55858.25 | E9: =E7+E8 -> 54301.25 | F9: =F7+F8 -> 56662.95 | G9: =G7+G8 -> 56095.68 | H9: =H7+H8 -> 55749.15 | I9: =I7+I8 -> 68320.66 | J9: =J7+J8 -> 68371.88 | ... AL9: =AL7+AL8 -> 122480.01
B10: Accounts Payable | C10: 3104 | D10: 3151 | E10: 2987 | F10: 4501 | G10: 3598 | H10: 3705 | I10: 3726 | J10: 3928 | K10: 4137 | L10: 4861 | M10: 5169 | N10: 7978 | O10: 3561 | P10: 3375 | Q10: 4469 | R10: 5123 | S10: 4497 | T10: 3799 | U10: 3741 | V10: 4610 | W10: 4417 | X10: 5002 | Y10: 6513 | Z10: 7395 | AA10: 4183 | AB10: 4208 | AC10: 4310 | AD10: 6129 | AE10: 5247 | AF10: 5854 | AG10: 4341 | AH10: 4873 | AI10: 5068 | AJ10: 5956 | AK10: 6152 | AL10: 9675
B11: Short-Term Loan | C11: 0 | D11: 0 | E11: 0 | F11: 0 | G11: 0 | H11: 0 | I11: 12000 | J11: 11500 | K11: 11000 | L11: 10500 | M11: 10000 | N11: 9500 | O11: 9000 | P11: 8500 | Q11: 8000 | R11: 7500 | S11: 7000 | T11: 6500 | U11: 6000 | V11: 5500 | W11: 5000 | X11: 4500 | Y11: 4000 | Z11: 3500 | AA11: 3000 | AB11: 2500 | AC11: 2000 | AD11: 1500 | AE11: 1000 | AF11: 500 | AG11: 0 | AH11: 0 | AI11: 0 | AJ11: 0 | AK11: 0 | AL11: 0
B12: Total Liabilities | C12: =C10+C11 -> 3104 | D12: =D10+D11 -> 3151 | E12: =E10+E11 -> 2987 | F12: =F10+F11 -> 4501 | G12: =G10+G11 -> 3598 | H12: =H10+H11 -> 3705 | I12: =I10+I11 -> 15726 | J12: =J10+J11 -> 15428 | ... AL12: =AL10+AL11 -> 9675
B13: Share Capital | C13: 41000 | D13: 41000 | E13: 41000 | F13: 41000 | G13: 41000 | H13: 41000 | I13: 41000 | J13: 41000 | K13: 41000 | L13: 41000 | M13: 41000 | N13: 41000 | O13: 41000 | P13: 41000 | Q13: 41000 | R13: 41000 | S13: 41000 | T13: 41000 | U13: 41000 | V13: 41000 | W13: 41000 | X13: 41000 | Y13: 41000 | Z13: 41000 | AA13: 41000 | AB13: 41000 | AC13: 41000 | AD13: 41000 | AE13: 41000 | AF13: 41000 | AG13: 41000 | AH13: 41000 | AI13: 41000 | AJ13: 41000 | AK13: 41000 | AL13: 41000
B14: Retained Earnings | C14: 12239 | D14: 11707.25 | E14: 10314.25 | F14: 11161.95 | G14: 11497.68 | H14: 11044.15 | I14: 11594.66 | J14: 11943.88 | K14: 11326.88 | L14: 12450.99 | M14: 15098.38 | N14: 22120.74 | O14: 21574.85 | P14: 19470.85 | Q14: 20909.34 | R14: 22030.41 | S14: 23183.03 | T14: 23630.13 | U14: 22757.88 | V14: 22750.63 | W14: 24761.78 | X14: 28505.35 | Y14: 32278.89 | Z14: 39159.66 | AA14: 39526.04 | AB14: 40604.16 | AC14: 42951.76 | AD14: 45277.19 | AE14: 46064.44 | AF14: 47097.91 | AG14: 48122.64 | AH14: 48560.35 | AI14: 50946.15 | AJ14: 55631.59 | AK14: 60501.84 | AL14: 71805.01
B15: Total Equity | C15: =C13+C14 -> 53239 | D15: =D13+D14 -> 52707.25 | E15: =E13+E14 -> 51314.25 | F15: =F13+F14 -> 52161.95 | G15: =G13+G14 -> 52497.68 | H15: =H13+H14 -> 52044.15 | I15: =I13+I14 -> 52594.66 | J15: =J13+J14 -> 52943.88 | ... AL15: =AL13+AL14 -> 112805.01
B16: Total Liabilities + Equity | C16: =C12+C15 -> 56343 | D16: =D12+D15 -> 55858.25 | E16: =E12+E15 -> 54301.25 | F16: =F12+F15 -> 56662.95 | G16: =G12+G15 -> 56095.68 | H16: =H12+H15 -> 55749.15 | I16: =I12+I15 -> 68320.66 | J16: =J12+J15 -> 68371.88 | ... AL16: =AL12+AL15 -> 122480.01
B17: Balance Check (should be 0) | C17: =C9-C16 -> 0 | D17: =D9-D16 -> 0 | E17: =E9-E16 -> 0 | F17: =F9-F16 -> 0 | G17: =G9-G16 -> 0 | H17: =H9-H16 -> 0 | I17: =I9-I16 -> 0 | J17: =J9-J16 -> 0 | ... AL17: =AL9-AL16 -> 0
B20: Assumptions:
B21: - Retained Earnings rolls forward from Net Profit on the Income Statement sheet, less monthly owner drawings.
B22: - Accounts Receivable ~ 14-18% of monthly revenue; Inventory ~ 1.1-1.3x monthly COGS; Accounts Payable ~ 18-25% of monthly COGS.
B23: - Fixed Assets held at cost (no depreciation modeled, for simplicity); two capex events: Jun-2023 ($3,500) and Aug-2024 ($6,000).
B24: - Short-Term Loan of $12,000 drawn Jul-2023 (matches Interest Expense start on Income Statement), repaid over 24 months at $500/month.
B25: - Owner drawings begin at $900/month, rising modestly over time.
B26: - Balance Check row confirms Total Assets = Total Liabilities + Equity every month (should read 0 throughout).

Sheet Cash Flow Statement
B1: RETAIL SME - CASH FLOW STATEMENT (Indirect Method, Monthly, Jan 2023 - Dec 2025, USD)
B3: Line Item | C3: Jan-23 | D3: Feb-23 | E3: Mar-23 | F3: Apr-23 | G3: May-23 | H3: Jun-23 | I3: Jul-23 | J3: Aug-23 | K3: Sep-23 | L3: Oct-23 | M3: Nov-23 | N3: Dec-23 | O3: Jan-24 | P3: Feb-24 | Q3: Mar-24 | R3: Apr-24 | S3: May-24 | T3: Jun-24 | U3: Jul-24 | V3: Aug-24 | W3: Sep-24 | X3: Oct-24 | Y3: Nov-24 | Z3: Dec-24 | AA3: Jan-25 | AB3: Feb-25 | AC3: Mar-25 | AD3: Apr-25 | AE3: May-25 | AF3: Jun-25 | AG3: Jul-25 | AH3: Aug-25 | AI3: Sep-25 | AJ3: Oct-25 | AK3: Nov-25 | AL3: Dec-25
B4: Net Profit (from Income Statement) | C4: ='Income Statement'!C22 -> -557 | D4: ='Income Statement'!D22 -> 375.25 | E4: ='Income Statement'!E22 -> -482 | F4: ='Income Statement'!F22 -> 1761.7 | G4: ='Income Statement'!G22 -> 1253.73 | H4: ='Income Statement'!H22 -> 468.47 | I4: ='Income Statement'!I22 -> 1476.51 | J4: ='Income Statement'!J22 -> 1278.22 | ... AL4: ='Income Statement'!AL22 -> 12342.17
B5: (Increase) / Decrease in Accounts Receivable | C5: =-('Balance Sheet'!C5-2200) -> -1222 | D5: =-('Balance Sheet'!D5-'Balance Sheet'!C5) -> -785 | E5: =-('Balance Sheet'!E5-'Balance Sheet'!D5) -> 308 | F5: =-('Balance Sheet'!F5-'Balance Sheet'!E5) -> -1091 | G5: =-('Balance Sheet'!G5-'Balance Sheet'!F5) -> 389 | H5: =-('Balance Sheet'!H5-'Balance Sheet'!G5) -> -451 | I5: =-('Balance Sheet'!I5-'Balance Sheet'!H5) -> -30 | J5: =-('Balance Sheet'!J5-'Balance Sheet'!I5) -> -282 | K5: =-('Balance Sheet'!K5-'Balance Sheet'!J5) -> 9 | ... AL5: =-('Balance Sheet'!AL5-'Balance Sheet'!AK5) -> -3614
B6: (Increase) / Decrease in Inventory | C6: =-('Balance Sheet'!C6-17000) -> -1503 | D6: =-('Balance Sheet'!D6-'Balance Sheet'!C6) -> -252 | E6: =-('Balance Sheet'!E6-'Balance Sheet'!D6) -> 2010 | F6: =-('Balance Sheet'!F6-'Balance Sheet'!E6) -> -6800 | G6: =-('Balance Sheet'!G6-'Balance Sheet'!F6) -> 3537 | H6: =-('Balance Sheet'!H6-'Balance Sheet'!G6) -> 5 | I6: =-('Balance Sheet'!I6-'Balance Sheet'!H6) -> 1460 | J6: =-('Balance Sheet'!J6-'Balance Sheet'!I6) -> -2071 | K6: =-('Balance Sheet'!K6-'Balance Sheet'!J6) -> -899 | ... AL6: =-('Balance Sheet'!AL6-'Balance Sheet'!AK6) -> -19586
B7: Increase / (Decrease) in Accounts Payable | C7: =('Balance Sheet'!C10-6500) -> -3396 | D7: =('Balance Sheet'!D10-'Balance Sheet'!C10) -> 47 | E7: =('Balance Sheet'!E10-'Balance Sheet'!D10) -> -164 | F7: =('Balance Sheet'!F10-'Balance Sheet'!E10) -> 1514 | G7: =('Balance Sheet'!G10-'Balance Sheet'!F10) -> -903 | H7: =('Balance Sheet'!H10-'Balance Sheet'!G10) -> 107 | I7: =('Balance Sheet'!I10-'Balance Sheet'!H10) -> 21 | J7: =('Balance Sheet'!J10-'Balance Sheet'!I10) -> 202 | K7: =('Balance Sheet'!K10-'Balance Sheet'!J10) -> 209 | ... AL7: =('Balance Sheet'!AL10-'Balance Sheet'!AK10) -> 3523
B8: Net Cash from Operating Activities | C8: =C4+C5+C6+C7 -> -6678 | D8: =D4+D5+D6+D7 -> -614.75 | E8: =E4+E5+E6+E7 -> 1672 | F8: =F4+F5+F6+F7 -> -4615.3 | G8: =G4+G5+G6+G7 -> 4276.73 | H8: =H4+H5+H6+H7 -> 129.47 | I8: =I4+I5+I6+I7 -> 2927.51 | J8: =J4+J5+J6+J7 -> -872.78 | ... AL8: =AL4+AL5+AL6+AL7 -> -7334.83
B9: Purchase of Fixed Assets (Capex) | C9: 0 | D9: 0 | E9: 0 | F9: 0 | G9: 0 | H9: -3500 | I9: 0 | J9: 0 | K9: 0 | L9: 0 | M9: 0 | N9: 0 | O9: 0 | P9: 0 | Q9: 0 | R9: 0 | S9: 0 | T9: 0 | U9: 0 | V9: -6000 | W9: 0 | X9: 0 | Y9: 0 | Z9: 0 | AA9: 0 | AB9: 0 | AC9: 0 | AD9: 0 | AE9: 0 | AF9: 0 | AG9: 0 | AH9: 0 | AI9: 0 | AJ9: 0 | AK9: 0 | AL9: 0
B10: Net Cash from Investing Activities | C10: =C9 -> 0 | D10: =D9 -> 0 | E10: =E9 -> 0 | F10: =F9 -> 0 | G10: =G9 -> 0 | H10: =H9 -> -3500 | I10: =I9 -> 0 | J10: =J9 -> 0 | ... AL10: =AL9 -> 0
B11: Loan Proceeds | C11: 0 | D11: 0 | E11: 0 | F11: 0 | G11: 0 | H11: 0 | I11: 12000 | J11: 0 | K11: 0 | L11: 0 | M11: 0 | N11: 0 | O11: 0 | P11: 0 | Q11: 0 | R11: 0 | S11: 0 | T11: 0 | U11: 0 | V11: 0 | W11: 0 | X11: 0 | Y11: 0 | Z11: 0 | AA11: 0 | AB11: 0 | AC11: 0 | AD11: 0 | AE11: 0 | AF11: 0 | AG11: 0 | AH11: 0 | AI11: 0 | AJ11: 0 | AK11: 0 | AL11: 0
B12: Loan Repayments | C12: 0 | D12: 0 | E12: 0 | F12: 0 | G12: 0 | H12: 0 | I12: 0 | J12: -500 | K12: -500 | L12: -500 | M12: -500 | N12: -500 | O12: -500 | P12: -500 | Q12: -500 | R12: -500 | S12: -500 | T12: -500 | U12: -500 | V12: -500 | W12: -500 | X12: -500 | Y12: -500 | Z12: -500 | AA12: -500 | AB12: -500 | AC12: -500 | AD12: -500 | AE12: -500 | AF12: -500 | AG12: -500 | AH12: 0 | AI12: 0 | AJ12: 0 | AK12: 0 | AL12: 0
B13: Owner Drawings | C13: -904 | D13: -907 | E13: -911 | F13: -914 | G13: -918 | H13: -922 | I13: -926 | J13: -929 | K13: -933 | L13: -937 | M13: -940 | N13: -944 | O13: -948 | P13: -952 | Q13: -956 | R13: -959 | S13: -963 | T13: -967 | U13: -971 | V13: -975 | W13: -979 | X13: -983 | Y13: -987 | Z13: -990 | AA13: -994 | AB13: -998 | AC13: -1002 | AD13: -1006 | AE13: -1010 | AF13: -1015 | AG13: -1019 | AH13: -1023 | AI13: -1027 | AJ13: -1031 | AK13: -1035 | AL13: -1039
B14: Net Cash from Financing Activities | C14: =C11+C12+C13 -> -904 | D14: =D11+D12+D13 -> -907 | E14: =E11+E12+E13 -> -911 | F14: =F11+F12+F13 -> -914 | G14: =G11+G12+G13 -> -918 | H14: =H11+H12+H13 -> -922 | I14: =I11+I12+I13 -> 11074 | J14: =J11+J12+J13 -> -1429 | ... AL14: =AL11+AL12+AL13 -> -1039
B15: Net Increase / (Decrease) in Cash | C15: =C8+C10+C14 -> -7582 | D15: =D8+D10+D14 -> -1521.75 | E15: =E8+E10+E14 -> 761 | F15: =F8+F10+F14 -> -5529.3 | G15: =G8+G10+G14 -> 3358.73 | H15: =H8+H10+H14 -> -4292.53 | I15: =I8+I10+I14 -> 14001.51 | J15: =J8+J10+J14 -> -2301.78 | ... AL15: =AL8+AL10+AL14 -> -8373.83
B16: Opening Cash Balance | C16: 22000 | D16: =C17 -> 14418 | E16: =D17 -> 12896.25 | F16: =E17 -> 13657.25 | G16: =F17 -> 8127.95 | H16: =G17 -> 11486.68 | I16: =H17 -> 7194.15 | J16: =I17 -> 21195.66 | K16: =J17 -> 18893.88 | ... AL16: =AK17 -> 37081.84
B17: Closing Cash Balance | C17: =C16+C15 -> 14418 | D17: =D16+D15 -> 12896.25 | E17: =E16+E15 -> 13657.25 | F17: =F16+F15 -> 8127.95 | G17: =G16+G15 -> 11486.68 | H17: =H16+H15 -> 7194.15 | I17: =I16+I15 -> 21195.66 | J17: =J16+J15 -> 18893.88 | ... AL17: =AL16+AL15 -> 28708.01
B18: Tie-out vs Balance Sheet Cash (should be 0) | C18: =C17-'Balance Sheet'!C4 -> 0 | D18: =D17-'Balance Sheet'!D4 -> 0 | E18: =E17-'Balance Sheet'!E4 -> 0 | F18: =F17-'Balance Sheet'!F4 -> 0 | G18: =G17-'Balance Sheet'!G4 -> 0 | H18: =H17-'Balance Sheet'!H4 -> 0 | I18: =I17-'Balance Sheet'!I4 -> 0 | J18: =J17-'Balance Sheet'!J4 -> 0 | ... AL18: =AL17-'Balance Sheet'!AL4 -> 0
B21: Assumptions:
B22: - Indirect method: starts from Net Profit, adjusts for working-capital movements (AR, Inventory, AP) sourced from the Balance Sheet.
B23: - Opening balances at Dec-2022 (pre-period): AR $2,200, Inventory $17,000, AP $6,500, Cash $22,000.
B24: - Capex, loan proceeds/repayments, and owner drawings are the same source figures used to build the Balance Sheet, so the statements tie out exactly.
B25: - Green cells link to another sheet (Income Statement / Balance Sheet). Blue cells are inputs. The Tie-out row confirms Closing Cash matches the Balance Sheet's Cash and Bank line every month.
